[{
		"question": "Поставьте галочки напротив ответа,который Вы считаете верным",
		"correct_answer": 0,
		"answers": [
			"Проезд запрещен",
			"Остановка запрещена",
			"Стоянка запрещена"
		]

	}, {
		"question": "Поставьте галочки напротив ответа,который Вы считаете верным",
		"correct_answer": 0,
		"answers": [
			"Остановка запрещена",
			"Проезд запрещен",
			"Стоянка запрещена"
		]

	},{
	   "question":"Поставьте галочки напротив ответа,который Вы считаете верным",
	   "correct_answer": 0,
	   "answers":[
	       "Ведется ремонтные работы",
		   "Движение запрещено",
		   "Не регулируемый перекресток"
	   
	   ]
		
	},{
	   "question":"Поставьте галочки напротив ответа,который Вы считаете верным",
	   "correct_answer": 0,
	   "answers":[
	       "Ведется ремонтные работы",
		   "Движение запрещено",
		   "Не регулируемый перекресток"
	   	     
	   ]
		
	},{
	   "question":"Поставьте галочки напротив ответа,который Вы считаете верным",
	   "correct_answer": 0,
	   "answers":[
	       "Дорогоа для трамвая,проезд запрещен",
		   "Не заезжать за стоп - линию",
		   "Окончание главной дороги"
	   	   	   
	   ]
	   	
	}


]